mousehumanizer/__init__.py
mousehumanizer/linux_controller.py
mousehumanizer/system_cursor.py
mousehumanizer/windows_controller.py
mousehumanizer/utilities/__init__.py
mousehumanizer/utilities/calculate_and_randomize.py
mousehumanizer/utilities/human_behavior.py
mousehumanizer/utilities/human_curve_generator.py
mousehumanizer-0.1.3.dist-info/METADATA
mousehumanizer-0.1.3.dist-info/WHEEL
mousehumanizer-0.1.3.dist-info/top_level.txt
mousehumanizer-0.1.3.dist-info/RECORD
