Metadata-Version: 2.2
Name: mousehumanizer
Version: 0.1.3
Summary: Human-like mouse automation for Windows and Linux
Home-page: https://github.com/Matt989MK/mouse-humanizer
Author: Matt Kielbasa
License: MIT
Requires-Dist: pynput
Dynamic: author
Dynamic: home-page
Dynamic: license
Dynamic: requires-dist
Dynamic: summary
